{"experiment_id": "ungar_high_card_demo", "episodes": [{"episode_index": 1, "total_reward": -1.0, "components": {"win_loss": -1.0, "baseline": 0.0}}, {"episode_index": 2, "total_reward": 0.0, "components": {"win_loss": 0.0, "baseline": 0.0}}, {"episode_index": 3, "total_reward": 1.0, "components": {"win_loss": 1.0, "baseline": 0.0}}, {"episode_index": 4, "total_reward": 1.0, "components": {"win_loss": 1.0, "baseline": 0.0}}, {"episode_index": 5, "total_reward": 1.0, "components": {"win_loss": 1.0, "baseline": 0.0}}, {"episode_index": 6, "total_reward": -1.0, "components": {"win_loss": -1.0, "baseline": 0.0}}, {"episode_index": 7, "total_reward": -1.0, "components": {"win_loss": -1.0, "baseline": 0.0}}, {"episode_index": 8, "total_reward": 1.0, "components": {"win_loss": 1.0, "baseline": 0.0}}, {"episode_index": 9, "total_reward": -1.0, "components": {"win_loss": -1.0, "baseline": 0.0}}, {"episode_index": 10, "total_reward": 1.0, "components": {"win_loss": 1.0, "baseline": 0.0}}]}